okabeito/__init__.py
okabeito-0.99.dist-info/LICENSE
okabeito-0.99.dist-info/METADATA
okabeito-0.99.dist-info/WHEEL
okabeito-0.99.dist-info/top_level.txt
okabeito-0.99.dist-info/RECORD
